utilless/__init__.py
utilless/comma.py
utilless/dot.py
utilless/iseven.py
utilless/isodd.py
utilless/strongpw.py
utilless-0.2.0.dist-info/LICENSE
utilless-0.2.0.dist-info/METADATA
utilless-0.2.0.dist-info/WHEEL
utilless-0.2.0.dist-info/top_level.txt
utilless-0.2.0.dist-info/RECORD
