Metadata-Version: 2.1
Name: utilless
Version: 0.2.0
Summary: Useless library if you have time for puzzles, a useful one if you don't
Home-page: https://github.com/hugotiburtino/utilless
Author: Hugo Tiburtino
License: Apache-2.0
Platform: UNKNOWN
